[{"id":0,"type":"","output_item_id":100288,"output_item_count":1,"time_to_craft_ms":0,"disciplines":["Mystic Forge"],"min_rating":0,"flags":["wiki"],"ingredients":[{"item_id":100466,"count":1},{"item_id":100267,"count":5},{"item_id":100098,"count":5},{"item_id":99964,"count":5}],"acquisition":{"vendors":[{"name":"Lyhr","cost":[{"amount":1,"item_name":"Gift of the Astral Ward","icon_url":"https://render.guildwars2.com/file/C47404C12AA33C0D69D7CBB5FEBC4412B9210C57/3122195.png","item_id":100466},{"amount":5,"item_name":"Case of Captured Lightning","icon_url":"https://render.guildwars2.com/file/6EAC5C9D6C6DB841D446C5C973E312C7F85179F1/3123706.png","item_id":100267},{"amount":5,"item_name":"Clot of Congealed Screams","icon_url":"https://render.guildwars2.com/file/E24EF5010A08319050EDA370367DFC9F71F4290F/3188139.png","item_id":100098},{"amount":5,"item_name":"Pouch of Stardust","icon_url":"https://render.guildwars2.com/file/E650550C0FA8A96D049B3CDFD561430259B969F1/3123704.png","item_id":99964},{"amount":10,"item_name":"Glob of Ectoplasm","icon_url":"https://render.guildwars2.com/file/18CE5D78317265000CF3C23ED76AB3CEE86BA60E/65941.png","item_id":19721}]}]}}]