[{"id":0,"type":"","output_item_id":100098,"output_item_count":1,"time_to_craft_ms":0,"disciplines":[],"min_rating":0,"flags":["wiki"],"ingredients":[],"acquisition":{"vendors":[{"name":"Astral Ward Mage (The Commons)","cost":[{"amount":250,"item_name":"Calcified Gasp","icon_url":"https://render.guildwars2.com/file/C264AC5057A0BE4EFA94D39C550256162EAAE8CD/3188138.png","item_id":101150}]},{"name":"Astral Ward Skirmisher (Memory&#39;s Hollow)","cost":[{"amount":250,"item_name":"Calcified Gasp","icon_url":"https://render.guildwars2.com/file/C264AC5057A0BE4EFA94D39C550256162EAAE8CD/3188138.png","item_id":101150}]},{"name":"Citadel of Zakiros: Commander&#39;s Choice Chest","cost":[{"amount":1,"item_name":"Citadel of Zakiros: Commander&#39;s Choice Chest","icon_url":"https://wiki.guildwars2.com/images/thumb/e/e5/Nayos_Hoard.png/20px-Nayos_Hoard.png"}]},{"name":"Gharr Leadclaw/Bulk Exchanges","cost":[{"amount":1,"item_name":"Inner Nayos: Commander&#39;s Choice Chest","icon_url":"https://wiki.guildwars2.com/images/thumb/e/e5/Nayos_Hoard.png/20px-Nayos_Hoard.png"}]},{"name":"Gharr Leadclaw/Bulk Exchanges","cost":[{"amount":1,"item_name":"Citadel of Zakiros: Commander&#39;s Choice Chest","icon_url":"https://wiki.guildwars2.com/images/thumb/e/e5/Nayos_Hoard.png/20px-Nayos_Hoard.png"}]},{"name":"Inner Nayos: Commander&#39;s Choice Chest","cost":[{"amount":1,"item_name":"Inner Nayos: Commander&#39;s Choice Chest","icon_url":"https://wiki.guildwars2.com/images/thumb/e/e5/Nayos_Hoard.png/20px-Nayos_Hoard.png"}]},{"name":"Portable Wizard&#39;s Tower Exchange/Bulk Exchanges","cost":[{"amount":1,"item_name":"Inner Nayos: Commander&#39;s Choice Chest","icon_url":"https://wiki.guildwars2.com/images/thumb/e/e5/Nayos_Hoard.png/20px-Nayos_Hoard.png"}]},{"name":"Portable Wizard&#39;s Tower Exchange/Bulk Exchanges","cost":[{"amount":1,"item_name":"Citadel of Zakiros: Commander&#39;s Choice Chest","icon_url":"https://wiki.guildwars2.com/images/thumb/e/e5/Nayos_Hoard.png/20px-Nayos_Hoard.png"}]},{"name":"Wizard&#39;s Gobbler/Horn of Maguuma/Bulk Exchanges","cost":[{"amount":1,"item_name":"Inner Nayos: Commander&#39;s Choice Chest","icon_url":"https://wiki.guildwars2.com/images/thumb/e/e5/Nayos_Hoard.png/20px-Nayos_Hoard.png"}]},{"name":"Wizard&#39;s Gobbler/Horn of Maguuma/Bulk Exchanges","cost":[{"amount":1,"item_name":"Citadel of Zakiros: Commander&#39;s Choice Chest","icon_url":"https://wiki.guildwars2.com/images/thumb/e/e5/Nayos_Hoard.png/20px-Nayos_Hoard.png"}]},{"name":"Citadel of Zakiros: Hero&#39;s Choice Chest","cost":[{"amount":1,"item_name":"Citadel of Zakiros: Hero&#39;s Choice Chest"}]},{"name":"Inner Nayos: Hero&#39;s Choice Chest","cost":[{"amount":1,"item_name":"Inner Nayos: Hero&#39;s Choice Chest"}]}]}}]