[{"id":0,"type":"","output_item_id":91559,"output_item_count":1,"time_to_craft_ms":0,"disciplines":["recipe sheet","huntsman, artificer, weaponsmith"],"min_rating":0,"flags":["wiki"],"ingredients":[{"item_id":89271,"count":10},{"item_id":24508,"count":5},{"item_id":19721,"count":10},{"item_id":89182,"count":2}],"acquisition":{"vendors":[{"name":"Al&#39;ir&#39;aska","cost":[{"amount":1,"item_name":"Al&#39;ir&#39;aska"}]},{"name":"Iron Hammer (loot)","cost":[{"amount":1,"item_name":"Iron Hammer (loot)"}]},{"name":"Iron Mace (loot)","cost":[{"amount":1,"item_name":"Iron Mace (loot)"}]},{"name":"Soft Wood Longbow (loot)","cost":[{"amount":1,"item_name":"Soft Wood Longbow (loot)"}]},{"name":"Soft Wood Scepter (loot)","cost":[{"amount":1,"item_name":"Soft Wood Scepter (loot)"}]},{"name":"Iron Rifle (loot)","cost":[{"amount":1,"item_name":"Iron Rifle (loot)"}]},{"name":"Iron Shield (loot)","cost":[{"amount":1,"item_name":"Iron Shield (loot)"}]},{"name":"Iron Sword (loot)","cost":[{"amount":1,"item_name":"Iron Sword (loot)"}]},{"name":"Combustion (scepter)","cost":[{"amount":1,"item_name":"Combustion (scepter)"}]},{"name":"Faithful","cost":[{"amount":1,"item_name":"Faithful","icon_url":"https://render.guildwars2.com/file/3EAA5320099B246F61F9A547A8E069ED419D0E63/340747.png","item_id":47091}]},{"name":"Faithful (account bound)","cost":[{"amount":1,"item_name":"Faithful (account bound)"}]},{"name":"Flame Legion Combat Blade","cost":[{"amount":1,"item_name":"Flame Legion Combat Blade"}]},{"name":"Flame Legion Flamesaw","cost":[{"amount":1,"item_name":"Flame Legion Flamesaw"}]},{"name":"Flame Legion Longshot","cost":[{"amount":1,"item_name":"Flame Legion Longshot"}]},{"name":"Flame Legion Pistol","cost":[{"amount":1,"item_name":"Flame Legion Pistol"}]},{"name":"Flame Legion Staff","cost":[{"amount":1,"item_name":"Flame Legion Staff"}]},{"name":"Incinerator","cost":[{"amount":1,"item_name":"Incinerator","icon_url":"https://render.guildwars2.com/file/D9B12A1EBEDC04047295CF0A66E43E650297D429/456012.png","item_id":95131}]},{"name":"Magmaton","cost":[{"amount":1,"item_name":"Magmaton","icon_url":"https://render.guildwars2.com/file/9ED941BD6F69AFE551FAF43407300119A2E2007D/340698.png","item_id":27638}]},{"name":"Mjölnir","cost":[{"amount":1,"item_name":"Mjölnir","icon_url":"https://render.guildwars2.com/file/9BB5C9BCD26C27B43AFA51029C4062AD506F6BEB/831722.png","item_id":31079}]},{"name":"Mystic Battlehammer","cost":[{"amount":1,"item_name":"Mystic Battlehammer","icon_url":"https://render.guildwars2.com/file/B70DA9CDDF027C7F6302610427696C5C7E333FFE/534334.png","item_id":31097}]},{"name":"Pact Brazier (Dragon&#39;s)","cost":[{"amount":1,"item_name":"Pact Brazier (Dragon&#39;s)"}]},{"name":"Pact Focus (Dragon&#39;s)","cost":[{"amount":1,"item_name":"Pact Focus (Dragon&#39;s)"}]},{"name":"Pact Herald (Dragon&#39;s)","cost":[{"amount":1,"item_name":"Pact Herald (Dragon&#39;s)"}]},{"name":"Pact Tower Shield (Dragon&#39;s)","cost":[{"amount":1,"item_name":"Pact Tower Shield (Dragon&#39;s)"}]},{"name":"Phoenix Reborn","cost":[{"amount":1,"item_name":"Phoenix Reborn","icon_url":"https://render.guildwars2.com/file/06576EA915551819314E749E53CB029634A20066/619849.png","item_id":44987}]},{"name":"Pumpkin Smasher","cost":[{"amount":1,"item_name":"Pumpkin Smasher","icon_url":"https://render.guildwars2.com/file/1A5753EA36BD606AFA64DD08241D5C2AE247D848/1203487.png","item_id":76131}]},{"name":"Iron Axe (loot)","cost":[{"amount":1,"item_name":"Iron Axe (loot)"}]},{"name":"Steam Speargun","cost":[{"amount":1,"item_name":"Steam Speargun","icon_url":"https://render.guildwars2.com/file/935CD7A5037BB9F3C46E0D770D2DD9730ED74A18/62495.png","item_id":75275}]},{"name":"Rodgort","cost":[{"amount":1,"item_name":"Rodgort","icon_url":"https://render.guildwars2.com/file/B1D6CB3AB4017633280ACDB36470F46829FDDD13/456027.png","item_id":95121}]},{"name":"Sunder","cost":[{"amount":1,"item_name":"Sunder","icon_url":"https://render.guildwars2.com/file/AD677EC744AAFC9809037378B7C4B7AC80B60902/340749.png","item_id":91088}]},{"name":"Titans&#39; Vengeance","cost":[{"amount":1,"item_name":"Titans&#39; Vengeance"}]},{"name":"Volcanus","cost":[{"amount":1,"item_name":"Volcanus","icon_url":"https://render.guildwars2.com/file/243263C29E975A9D5169BBA7B14803C21FA857D5/780636.png","item_id":31053}]}]}}]